examples/README.md
examples/01_Basic_Usage/basic_charts.py
examples/01_Basic_Usage/error_handling.py
examples/01_Basic_Usage/heatmaps.py
examples/01_Basic_Usage/multi_plot_grid.py
examples/02_Chart_Types/bar_charts.py
examples/02_Chart_Types/candlestick.py
examples/02_Chart_Types/heatmaps.py
examples/02_Chart_Types/line_charts.py
examples/02_Chart_Types/pie_and_donut.py
examples/02_Chart_Types/polar_plots.py
examples/02_Chart_Types/statistical_plots.py
examples/02_Chart_Types/waterfall.py
examples/03_Layout_Management/advanced_layout.py
examples/03_Layout_Management/aspect_ratio.py
examples/03_Layout_Management/block_span.py
examples/03_Layout_Management/layout_showcase.py
examples/03_Layout_Management/layouttester.py
examples/03_Layout_Management/manual_layout_demo.py
examples/03_Layout_Management/nested_layout.py
examples/03_Layout_Management/row_span.py
examples/04_Twin_Axes/basic_twin_axes.py
examples/04_Twin_Axes/polar_twin_axes.py
examples/04_Twin_Axes/twin_axes_color_cycle.py
examples/05_Styling_and_Themes/aesthetics.py
examples/05_Styling_and_Themes/cleanup_demonstration.py
examples/05_Styling_and_Themes/custom_styles.py
examples/05_Styling_and_Themes/feature_expansion.py
examples/05_Styling_and_Themes/global_styling.py
examples/05_Styling_and_Themes/statistical_plots.py
examples/05_Styling_and_Themes/style_gallery.py
examples/06_Annotations/shapes_and_regions/highlighting.py
examples/06_Annotations/shapes_and_regions/shapes_and_boxes.py
examples/06_Annotations/shapes_and_regions/zoom_insets.py
examples/06_Annotations/statistical/statistical_annotation.py
examples/06_Annotations/text_and_labels/figure_text.py
examples/06_Annotations/text_and_labels/subplot_labels_auto.py
examples/06_Annotations/text_and_labels/subplot_labels_custom.py
examples/06_Annotations/text_and_labels/subplot_labels_grouped.py
examples/06_Annotations/text_and_labels/subplot_labels_nested.py
examples/07_Images_and_Composition/composite_figures.py
paperplotter-0.1.14.dist-info/licenses/LICENSE
paperplotter-0.1.14.dist-info/METADATA
paperplotter-0.1.14.dist-info/WHEEL
paperplotter-0.1.14.dist-info/top_level.txt
paperplotter-0.1.14.dist-info/RECORD
