Metadata-Version: 2.4
Name: paperplotter
Version: 0.1.14
Summary: 一个为科研论文设计的声明式 Matplotlib 封装库，让复杂图表的创建变得简单直观。
Author-email: VerNe <yuu_seeing@foxmail.com>
License-Expression: MIT
Project-URL: Homepage, https://github.com/ID-VerNe/PaperPlot
Project-URL: Bug Tracker, https://github.com/ID-VerNe/PaperPlot/issues
Classifier: Programming Language :: Python :: 3
Classifier: Operating System :: OS Independent
Classifier: Framework :: Matplotlib
Classifier: Intended Audience :: Science/Research
Classifier: Topic :: Scientific/Engineering :: Visualization
Requires-Python: >=3.8
License-File: LICENSE
Requires-Dist: matplotlib>=3.5.0
Requires-Dist: numpy>=1.21.0
Requires-Dist: pandas>=1.3.0
Requires-Dist: seaborn>=0.11.0
Requires-Dist: scipy==1.16.3
Requires-Dist: adjustText==1.3.0
Dynamic: license-file
